df_test_framework/__init__.py
df_test_framework/bootstrap/__init__.py
df_test_framework/bootstrap/bootstrap.py
df_test_framework/bootstrap/providers.py
df_test_framework/bootstrap/runtime.py
df_test_framework/capabilities/__init__.py
df_test_framework/capabilities/clients/__init__.py
df_test_framework/capabilities/clients/graphql/__init__.py
df_test_framework/capabilities/clients/graphql/client.py
df_test_framework/capabilities/clients/graphql/models.py
df_test_framework/capabilities/clients/graphql/query_builder.py
df_test_framework/capabilities/clients/graphql/middleware/__init__.py
df_test_framework/capabilities/clients/graphql/middleware/base.py
df_test_framework/capabilities/clients/graphql/middleware/event_publisher.py
df_test_framework/capabilities/clients/graphql/middleware/logging.py
df_test_framework/capabilities/clients/graphql/middleware/retry.py
df_test_framework/capabilities/clients/grpc/__init__.py
df_test_framework/capabilities/clients/grpc/client.py
df_test_framework/capabilities/clients/grpc/models.py
df_test_framework/capabilities/clients/grpc/middleware/__init__.py
df_test_framework/capabilities/clients/grpc/middleware/base.py
df_test_framework/capabilities/clients/grpc/middleware/event_publisher.py
df_test_framework/capabilities/clients/grpc/middleware/logging.py
df_test_framework/capabilities/clients/grpc/middleware/metadata.py
df_test_framework/capabilities/clients/grpc/middleware/retry.py
df_test_framework/capabilities/clients/grpc/middleware/timing.py
df_test_framework/capabilities/clients/http/__init__.py
df_test_framework/capabilities/clients/http/core/__init__.py
df_test_framework/capabilities/clients/http/core/request.py
df_test_framework/capabilities/clients/http/core/response.py
df_test_framework/capabilities/clients/http/middleware/__init__.py
df_test_framework/capabilities/clients/http/middleware/auth.py
df_test_framework/capabilities/clients/http/middleware/event_publisher.py
df_test_framework-4.0.0.dist-info/METADATA
df_test_framework-4.0.0.dist-info/WHEEL
df_test_framework-4.0.0.dist-info/entry_points.txt
df_test_framework-4.0.0.dist-info/RECORD
