Metadata-Version: 2.4
Name: df-test-framework
Version: 4.0.0
Summary: 基于交互模式的现代化测试自动化框架，支持多种测试场景
Project-URL: Homepage, https://github.com/yourorg/df-test-framework
Project-URL: Repository, https://github.com/yourorg/df-test-framework
Project-URL: Documentation, https://github.com/yourorg/df-test-framework#readme
Project-URL: Bug Tracker, https://github.com/yourorg/df-test-framework/issues
Author-email: DF QA Team <qa@example.com>
License: MIT
Keywords: api,automation,framework,pytest,testing,ui
Classifier: Development Status :: 4 - Beta
Classifier: Framework :: Pytest
Classifier: Intended Audience :: Developers
Classifier: License :: OSI Approved :: MIT License
Classifier: Programming Language :: Python :: 3
Classifier: Programming Language :: Python :: 3.12
Classifier: Programming Language :: Python :: 3.13
Classifier: Topic :: Software Development :: Quality Assurance
Classifier: Topic :: Software Development :: Testing
Requires-Python: >=3.12
Requires-Dist: allure-pytest>=2.13.0
Requires-Dist: assertpy>=1.1
Requires-Dist: faker>=38.2.0
Requires-Dist: filelock>=3.20.1
Requires-Dist: freezegun>=1.5.0
Requires-Dist: h2>=4.3.0
Requires-Dist: hpack>=4.1.0
Requires-Dist: httpx>=0.27.0
Requires-Dist: hyperframe>=6.1.0
Requires-Dist: jsonpath-ng>=1.7.0
Requires-Dist: jsonschema-spec>=0.2.4
Requires-Dist: jsonschema>=4.25.1
Requires-Dist: openpyxl>=3.1.0
Requires-Dist: pluggy>=1.5.0
Requires-Dist: prance[osv]>=23.6.0
Requires-Dist: pydantic-settings>=2.0.0
Requires-Dist: pydantic>=2.0.0
Requires-Dist: pymysql>=1.1.0
Requires-Dist: pypinyin>=0.53.0
Requires-Dist: pytest-asyncio>=1.3.0
Requires-Dist: pytest-timeout>=2.2.0
Requires-Dist: pytest>=9.0.1
Requires-Dist: python-dotenv>=1.0.0
Requires-Dist: pyyaml>=6.0.0
Requires-Dist: questionary>=2.0.0
Requires-Dist: redis>=5.0.0
Requires-Dist: requests>=2.32.4
Requires-Dist: sqlalchemy>=2.0.0
Requires-Dist: structlog>=25.4.0
Requires-Dist: urllib3>=2.6.0
Provides-Extra: all
Requires-Dist: aiomysql>=0.2.0; extra == 'all'
Requires-Dist: aiosqlite>=0.20.0; extra == 'all'
Requires-Dist: asyncpg>=0.29.0; extra == 'all'
Requires-Dist: boto3>=1.34.0; extra == 'all'
Requires-Dist: confluent-kafka>=2.12.0; extra == 'all'
Requires-Dist: opentelemetry-api>=1.20.0; extra == 'all'
Requires-Dist: opentelemetry-instrumentation-httpx>=0.41b0; extra == 'all'
Requires-Dist: opentelemetry-sdk>=1.20.0; extra == 'all'
Requires-Dist: orjson>=3.9.0; extra == 'all'
Requires-Dist: oss2>=2.18.0; extra == 'all'
Requires-Dist: pika>=1.3.0; extra == 'all'
Requires-Dist: playwright>=1.40.0; extra == 'all'
Requires-Dist: prometheus-client>=0.19.0; extra == 'all'
Requires-Dist: pypinyin>=0.53.0; extra == 'all'
Requires-Dist: rocketmq-python-client>=5.0.0; extra == 'all'
Requires-Dist: selenium>=4.0.0; extra == 'all'
Provides-Extra: codegen
Requires-Dist: pypinyin>=0.53.0; extra == 'codegen'
Provides-Extra: database-async
Requires-Dist: aiomysql>=0.2.0; extra == 'database-async'
Requires-Dist: aiosqlite>=0.20.0; extra == 'database-async'
Requires-Dist: asyncpg>=0.29.0; extra == 'database-async'
Provides-Extra: kafka
Requires-Dist: confluent-kafka>=2.12.0; extra == 'kafka'
Provides-Extra: mq
Requires-Dist: confluent-kafka>=2.12.0; extra == 'mq'
Requires-Dist: pika>=1.3.0; extra == 'mq'
Requires-Dist: rocketmq-python-client>=5.0.0; extra == 'mq'
Provides-Extra: observability
Requires-Dist: opentelemetry-api>=1.20.0; extra == 'observability'
Requires-Dist: opentelemetry-instrumentation-httpx>=0.41b0; extra == 'observability'
Requires-Dist: opentelemetry-sdk>=1.20.0; extra == 'observability'
Requires-Dist: prometheus-client>=0.19.0; extra == 'observability'
Provides-Extra: opentelemetry
Requires-Dist: opentelemetry-api>=1.20.0; extra == 'opentelemetry'
Requires-Dist: opentelemetry-instrumentation-httpx>=0.41b0; extra == 'opentelemetry'
Requires-Dist: opentelemetry-sdk>=1.20.0; extra == 'opentelemetry'
Provides-Extra: performance
Requires-Dist: orjson>=3.9.0; extra == 'performance'
Provides-Extra: prometheus
Requires-Dist: prometheus-client>=0.19.0; extra == 'prometheus'
Provides-Extra: rabbitmq
Requires-Dist: pika>=1.3.0; extra == 'rabbitmq'
Provides-Extra: rocketmq
Requires-Dist: rocketmq-python-client>=5.0.0; extra == 'rocketmq'
Provides-Extra: storage
Requires-Dist: boto3>=1.34.0; extra == 'storage'
Requires-Dist: oss2>=2.18.0; extra == 'storage'
Provides-Extra: ui
Requires-Dist: playwright>=1.40.0; extra == 'ui'
Requires-Dist: selenium>=4.0.0; extra == 'ui'
